[
      { "en_word": "apple", "uz_word": "olma" },
      { "en_word": "banana", "uz_word": "banan" },
      { "en_word": "car", "uz_word": "mashina" },
      { "en_word": "house", "uz_word": "uy" },
      { "en_word": "dog", "uz_word": "it" },
      { "en_word": "cat", "uz_word": "muxlis" },
      { "en_word": "book", "uz_word": "kitob" },
      { "en_word": "computer", "uz_word": "kompyuter" },
      { "en_word": "phone", "uz_word": "telefon" },
      { "en_word": "table", "uz_word": "stol" },
      { "en_word": "chair", "uz_word": "stul" },
      { "en_word": "pen", "uz_word": "qalam" },
      { "en_word": "pencil", "uz_word": "ruchka" },
      { "en_word": "school", "uz_word": "maktab" },
      { "en_word": "teacher", "uz_word": "o'qituvchi" },
      { "en_word": "student", "uz_word": "o'quvchi" },
      { "en_word": "university", "uz_word": "universitet" },
      { "en_word": "language", "uz_word": "til" },
      { "en_word": "friend", "uz_word": "do'st" },
      { "en_word": "family", "uz_word": "oilaviy" },
      { "en_word": "love", "uz_word": "sevgi" },
      { "en_word": "happiness", "uz_word": "baxt" },
      { "en_word": "sadness", "uz_word": "qayg'u" },
      { "en_word": "joy", "uz_word": "sho'xlik" },
      { "en_word": "anger", "uz_word": "juda" },
      { "en_word": "fear", "uz_word": "qo'rqinch" },
      { "en_word": "courage", "uz_word": "jasorat" },
      { "en_word": "peace", "uz_word": "tinchlik" },
      { "en_word": "war", "uz_word": "urush" },
      { "en_word": "nature", "uz_word": "tabiat" },
      { "en_word": "tree", "uz_word": "daraxt" },
      { "en_word": "flower", "uz_word": "gul" },
      { "en_word": "river", "uz_word": "daryo" },
      { "en_word": "mountain", "uz_word": "tog'" },
      { "en_word": "sky", "uz_word": "osmon" },
      { "en_word": "sun", "uz_word": "quyosh" },
      { "en_word": "moon", "uz_word": "oy" },
      { "en_word": "star", "uz_word": "yulduz" },
      { "en_word": "planet", "uz_word": "planeta" },
      { "en_word": "space", "uz_word": "bo'sh oyna" },
      { "en_word": "time", "uz_word": "vaqt" },
      { "en_word": "clock", "uz_word": "soat" },
      { "en_word": "hour", "uz_word": "soat" },
      { "en_word": "minute", "uz_word": "daqiqa" },
      { "en_word": "second", "uz_word": "soniya" }
]